<?xml version="1.0" encoding="UTF-8"?>
<con:soapui-project id="f7752344-de74-4ced-a4ed-ff1e2f6af95d" activeEnvironment="Default" name="RESTAndSOAP_Project" resourceRoot="" soapui-version="5.7.0" abortOnError="false" runType="SEQUENTIAL" xmlns:con="http://eviware.com/soapui/config"><con:settings/><con:interface xsi:type="con:RestService" id="fac9a87f-ca22-4a6b-a500-ef5491dcf9d8" wadlVersion="http://wadl.dev.java.net/2009/02" name="https://restcountries.com" type="rest" xmlns:xsi="http://www.w3.org/2001/XMLSchema-instance"><con:settings/><con:definitionCache type="TEXT" rootPart=""/><con:endpoints><con:endpoint>https://restcountries.com</con:endpoint></con:endpoints><con:resource name="All" path="/v3.1/all" id="f8888b00-fb1c-4029-9433-1d7674ad094d"><con:settings/><con:parameters/><con:method name="All 1" id="1327a1fd-3909-4f2b-84f3-b0bd7ba2299a" method="GET"><con:settings/><con:parameters/><con:representation type="RESPONSE"><con:mediaType>application/json</con:mediaType><con:status>200</con:status><con:params/><con:element>Response</con:element></con:representation><con:request name="Request 1" id="9880d2f8-95d3-4672-b00a-6180a44ca53c" mediaType="application/json"><con:settings><con:setting id="com.eviware.soapui.impl.wsdl.WsdlRequest@request-headers">&lt;xml-fragment/></con:setting></con:settings><con:endpoint>https://restcountries.com</con:endpoint><con:request/><con:originalUri>https://restcountries.com/v3.1/all</con:originalUri><con:credentials><con:authType>No Authorization</con:authType></con:credentials><con:jmsConfig JMSDeliveryMode="PERSISTENT"/><con:jmsPropertyConfig/><con:parameters/></con:request></con:method></con:resource></con:interface><con:interface xsi:type="con:RestService" id="615db328-7853-4760-b4c8-bd340edae3f2" wadlVersion="http://wadl.dev.java.net/2009/02" name="https://restcountries.com" type="rest" xmlns:xsi="http://www.w3.org/2001/XMLSchema-instance"><con:settings/><con:definitionCache type="TEXT" rootPart=""/><con:endpoints><con:endpoint>https://restcountries.com</con:endpoint></con:endpoints><con:resource name="United" path="/v3.1/name/{countryName}" id="e18ab426-3893-4bea-ad13-f2277715315a"><con:settings/><con:parameters><con:parameter required="false"><con:name>countryName</con:name><con:value/><con:style>TEMPLATE</con:style><con:default/><con:description xsi:nil="true"/></con:parameter></con:parameters><con:method name="United 1" id="bc76c32d-42ca-4427-82cf-ae29d1ab6822" method="GET"><con:settings/><con:parameters/><con:representation type="RESPONSE"><con:mediaType>application/json</con:mediaType><con:status>200</con:status><con:params/><con:element>Response</con:element></con:representation><con:representation type="FAULT"><con:mediaType>application/json</con:mediaType><con:status>404</con:status><con:params/><con:element xmlns:unit="https://restcountries.com/v3.1/name/united">unit:Fault</con:element></con:representation><con:request name="Request 1" id="bd31fe7c-cff3-418a-954f-07500b155dcf" mediaType="application/json"><con:settings><con:setting id="com.eviware.soapui.impl.wsdl.WsdlRequest@request-headers">&lt;xml-fragment/></con:setting></con:settings><con:endpoint>https://restcountries.com</con:endpoint><con:request/><con:originalUri>https://restcountries.com/v3.1/name/united</con:originalUri><con:credentials><con:authType>No Authorization</con:authType></con:credentials><con:jmsConfig JMSDeliveryMode="PERSISTENT"/><con:jmsPropertyConfig/><con:parameters><entry key="countryName" value="canada" xmlns="http://eviware.com/soapui/config"/></con:parameters><con:parameterOrder><con:entry>countryName</con:entry></con:parameterOrder></con:request></con:method></con:resource></con:interface><con:interface xsi:type="con:RestService" id="6d59289c-1771-4a0e-a210-e6a23bf522e4" wadlVersion="http://wadl.dev.java.net/2009/02" name="https://restcountries.com" type="rest" xmlns:xsi="http://www.w3.org/2001/XMLSchema-instance"><con:settings/><con:definitionCache/><con:endpoints><con:endpoint>https://restcountries.com</con:endpoint></con:endpoints><con:resource name="Aruba" path="/v3.1/name/aruba" id="e2bc2b13-98b1-4a15-94fb-ab5e492a64c0"><con:settings/><con:parameters><con:parameter><con:name>fullText</con:name><con:value>true</con:value><con:style>QUERY</con:style><con:default>true</con:default><con:path xsi:nil="true"/><con:description xsi:nil="true"/></con:parameter></con:parameters><con:method name="Aruba 1" id="14976a74-1aa0-40af-a98a-a11c010cfb42" method="GET"><con:settings/><con:parameters/><con:representation type="RESPONSE"><con:mediaType>application/json</con:mediaType><con:status>200</con:status><con:params/><con:element>Response</con:element></con:representation><con:request name="Request 1" id="2d85490c-0d8f-4c0d-b70e-eff443a29916" mediaType="application/json"><con:settings><con:setting id="com.eviware.soapui.impl.wsdl.WsdlRequest@request-headers">&lt;xml-fragment/></con:setting></con:settings><con:endpoint>https://restcountries.com</con:endpoint><con:request/><con:originalUri>https://restcountries.com/v3.1/name/aruba</con:originalUri><con:credentials><con:authType>No Authorization</con:authType></con:credentials><con:jmsConfig JMSDeliveryMode="PERSISTENT"/><con:jmsPropertyConfig/><con:parameters><entry key="fullText" value="true" xmlns="http://eviware.com/soapui/config"/></con:parameters><con:parameterOrder><con:entry>fullText</con:entry></con:parameterOrder></con:request></con:method></con:resource></con:interface><con:interface xsi:type="con:WsdlInterface" id="55a6c908-f697-4091-8f82-20869fc86f95" wsaVersion="NONE" name="CountryInfoServiceSoapBinding" type="wsdl" bindingName="{http://www.oorsprong.org/websamples.countryinfo}CountryInfoServiceSoapBinding" soapVersion="1_1" anonymous="optional" definition="http://webservices.oorsprong.org/websamples.countryinfo/CountryInfoService.wso?WSDL" xmlns:xsi="http://www.w3.org/2001/XMLSchema-instance"><con:settings/><con:definitionCache type="TEXT" rootPart="http://webservices.oorsprong.org/websamples.countryinfo/CountryInfoService.wso?WSDL"><con:part><con:url>http://webservices.oorsprong.org/websamples.countryinfo/CountryInfoService.wso?WSDL</con:url><con:content><![CDATA[<definitions name="CountryInfoService" targetNamespace="http://www.oorsprong.org/websamples.countryinfo" xmlns="http://schemas.xmlsoap.org/wsdl/" xmlns:xs="http://www.w3.org/2001/XMLSchema" xmlns:soap="http://schemas.xmlsoap.org/wsdl/soap/" xmlns:soap12="http://schemas.xmlsoap.org/wsdl/soap12/" xmlns:tns="http://www.oorsprong.org/websamples.countryinfo">
  <types>
    <xs:schema elementFormDefault="qualified" targetNamespace="http://www.oorsprong.org/websamples.countryinfo">
      <xs:complexType name="tContinent">
        <xs:sequence>
          <xs:element name="sCode" type="xs:string"/>
          <xs:element name="sName" type="xs:string"/>
        </xs:sequence>
      </xs:complexType>
      <xs:complexType name="tCurrency">
        <xs:sequence>
          <xs:element name="sISOCode" type="xs:string"/>
          <xs:element name="sName" type="xs:string"/>
        </xs:sequence>
      </xs:complexType>
      <xs:complexType name="tCountryCodeAndName">
        <xs:sequence>
          <xs:element name="sISOCode" type="xs:string"/>
          <xs:element name="sName" type="xs:string"/>
        </xs:sequence>
      </xs:complexType>
      <xs:complexType name="tCountryCodeAndNameGroupedByContinent">
        <xs:sequence>
          <xs:element name="Continent" type="tns:tContinent"/>
          <xs:element name="CountryCodeAndNames" type="tns:ArrayOftCountryCodeAndName"/>
        </xs:sequence>
      </xs:complexType>
      <xs:complexType name="tCountryInfo">
        <xs:sequence>
          <xs:element name="sISOCode" type="xs:string"/>
          <xs:element name="sName" type="xs:string"/>
          <xs:element name="sCapitalCity" type="xs:string"/>
          <xs:element name="sPhoneCode" type="xs:string"/>
          <xs:element name="sContinentCode" type="xs:string"/>
          <xs:element name="sCurrencyISOCode" type="xs:string"/>
          <xs:element name="sCountryFlag" type="xs:string"/>
          <xs:element name="Languages" type="tns:ArrayOftLanguage"/>
        </xs:sequence>
      </xs:complexType>
      <xs:complexType name="tLanguage">
        <xs:sequence>
          <xs:element name="sISOCode" type="xs:string"/>
          <xs:element name="sName" type="xs:string"/>
        </xs:sequence>
      </xs:complexType>
      <xs:complexType name="ArrayOftCountryCodeAndName">
        <xs:sequence>
          <xs:element name="tCountryCodeAndName" type="tns:tCountryCodeAndName" minOccurs="0" maxOccurs="unbounded" nillable="true"/>
        </xs:sequence>
      </xs:complexType>
      <xs:complexType name="ArrayOftLanguage">
        <xs:sequence>
          <xs:element name="tLanguage" type="tns:tLanguage" minOccurs="0" maxOccurs="unbounded" nillable="true"/>
        </xs:sequence>
      </xs:complexType>
      <xs:complexType name="ArrayOftContinent">
        <xs:sequence>
          <xs:element name="tContinent" type="tns:tContinent" minOccurs="0" maxOccurs="unbounded" nillable="true"/>
        </xs:sequence>
      </xs:complexType>
      <xs:complexType name="ArrayOftCurrency">
        <xs:sequence>
          <xs:element name="tCurrency" type="tns:tCurrency" minOccurs="0" maxOccurs="unbounded" nillable="true"/>
        </xs:sequence>
      </xs:complexType>
      <xs:complexType name="ArrayOftCountryCodeAndNameGroupedByContinent">
        <xs:sequence>
          <xs:element name="tCountryCodeAndNameGroupedByContinent" type="tns:tCountryCodeAndNameGroupedByContinent" minOccurs="0" maxOccurs="unbounded" nillable="true"/>
        </xs:sequence>
      </xs:complexType>
      <xs:complexType name="ArrayOftCountryInfo">
        <xs:sequence>
          <xs:element name="tCountryInfo" type="tns:tCountryInfo" minOccurs="0" maxOccurs="unbounded" nillable="true"/>
        </xs:sequence>
      </xs:complexType>
      <xs:element name="ListOfContinentsByName">
        <xs:complexType>
          <xs:sequence/>
        </xs:complexType>
      </xs:element>
      <xs:element name="ListOfContinentsByNameResponse">
        <xs:complexType>
          <xs:sequence>
            <xs:element name="ListOfContinentsByNameResult" type="tns:ArrayOftContinent"/>
          </xs:sequence>
        </xs:complexType>
      </xs:element>
      <xs:element name="ListOfContinentsByCode">
        <xs:complexType>
          <xs:sequence/>
        </xs:complexType>
      </xs:element>
      <xs:element name="ListOfContinentsByCodeResponse">
        <xs:complexType>
          <xs:sequence>
            <xs:element name="ListOfContinentsByCodeResult" type="tns:ArrayOftContinent"/>
          </xs:sequence>
        </xs:complexType>
      </xs:element>
      <xs:element name="ListOfCurrenciesByName">
        <xs:complexType>
          <xs:sequence/>
        </xs:complexType>
      </xs:element>
      <xs:element name="ListOfCurrenciesByNameResponse">
        <xs:complexType>
          <xs:sequence>
            <xs:element name="ListOfCurrenciesByNameResult" type="tns:ArrayOftCurrency"/>
          </xs:sequence>
        </xs:complexType>
      </xs:element>
      <xs:element name="ListOfCurrenciesByCode">
        <xs:complexType>
          <xs:sequence/>
        </xs:complexType>
      </xs:element>
      <xs:element name="ListOfCurrenciesByCodeResponse">
        <xs:complexType>
          <xs:sequence>
            <xs:element name="ListOfCurrenciesByCodeResult" type="tns:ArrayOftCurrency"/>
          </xs:sequence>
        </xs:complexType>
      </xs:element>
      <xs:element name="CurrencyName">
        <xs:complexType>
          <xs:sequence>
            <xs:element name="sCurrencyISOCode" type="xs:string"/>
          </xs:sequence>
        </xs:complexType>
      </xs:element>
      <xs:element name="CurrencyNameResponse">
        <xs:complexType>
          <xs:sequence>
            <xs:element name="CurrencyNameResult" type="xs:string"/>
          </xs:sequence>
        </xs:complexType>
      </xs:element>
      <xs:element name="ListOfCountryNamesByCode">
        <xs:complexType>
          <xs:sequence/>
        </xs:complexType>
      </xs:element>
      <xs:element name="ListOfCountryNamesByCodeResponse">
        <xs:complexType>
          <xs:sequence>
            <xs:element name="ListOfCountryNamesByCodeResult" type="tns:ArrayOftCountryCodeAndName"/>
          </xs:sequence>
        </xs:complexType>
      </xs:element>
      <xs:element name="ListOfCountryNamesByName">
        <xs:complexType>
          <xs:sequence/>
        </xs:complexType>
      </xs:element>
      <xs:element name="ListOfCountryNamesByNameResponse">
        <xs:complexType>
          <xs:sequence>
            <xs:element name="ListOfCountryNamesByNameResult" type="tns:ArrayOftCountryCodeAndName"/>
          </xs:sequence>
        </xs:complexType>
      </xs:element>
      <xs:element name="ListOfCountryNamesGroupedByContinent">
        <xs:complexType>
          <xs:sequence/>
        </xs:complexType>
      </xs:element>
      <xs:element name="ListOfCountryNamesGroupedByContinentResponse">
        <xs:complexType>
          <xs:sequence>
            <xs:element name="ListOfCountryNamesGroupedByContinentResult" type="tns:ArrayOftCountryCodeAndNameGroupedByContinent"/>
          </xs:sequence>
        </xs:complexType>
      </xs:element>
      <xs:element name="CountryName">
        <xs:complexType>
          <xs:sequence>
            <xs:element name="sCountryISOCode" type="xs:string"/>
          </xs:sequence>
        </xs:complexType>
      </xs:element>
      <xs:element name="CountryNameResponse">
        <xs:complexType>
          <xs:sequence>
            <xs:element name="CountryNameResult" type="xs:string"/>
          </xs:sequence>
        </xs:complexType>
      </xs:element>
      <xs:element name="CountryISOCode">
        <xs:complexType>
          <xs:sequence>
            <xs:element name="sCountryName" type="xs:string"/>
          </xs:sequence>
        </xs:complexType>
      </xs:element>
      <xs:element name="CountryISOCodeResponse">
        <xs:complexType>
          <xs:sequence>
            <xs:element name="CountryISOCodeResult" type="xs:string"/>
          </xs:sequence>
        </xs:complexType>
      </xs:element>
      <xs:element name="CapitalCity">
        <xs:complexType>
          <xs:sequence>
            <xs:element name="sCountryISOCode" type="xs:string"/>
          </xs:sequence>
        </xs:complexType>
      </xs:element>
      <xs:element name="CapitalCityResponse">
        <xs:complexType>
          <xs:sequence>
            <xs:element name="CapitalCityResult" type="xs:string"/>
          </xs:sequence>
        </xs:complexType>
      </xs:element>
      <xs:element name="CountryCurrency">
        <xs:complexType>
          <xs:sequence>
            <xs:element name="sCountryISOCode" type="xs:string"/>
          </xs:sequence>
        </xs:complexType>
      </xs:element>
      <xs:element name="CountryCurrencyResponse">
        <xs:complexType>
          <xs:sequence>
            <xs:element name="CountryCurrencyResult" type="tns:tCurrency"/>
          </xs:sequence>
        </xs:complexType>
      </xs:element>
      <xs:element name="CountryFlag">
        <xs:complexType>
          <xs:sequence>
            <xs:element name="sCountryISOCode" type="xs:string"/>
          </xs:sequence>
        </xs:complexType>
      </xs:element>
      <xs:element name="CountryFlagResponse">
        <xs:complexType>
          <xs:sequence>
            <xs:element name="CountryFlagResult" type="xs:string"/>
          </xs:sequence>
        </xs:complexType>
      </xs:element>
      <xs:element name="CountryIntPhoneCode">
        <xs:complexType>
          <xs:sequence>
            <xs:element name="sCountryISOCode" type="xs:string"/>
          </xs:sequence>
        </xs:complexType>
      </xs:element>
      <xs:element name="CountryIntPhoneCodeResponse">
        <xs:complexType>
          <xs:sequence>
            <xs:element name="CountryIntPhoneCodeResult" type="xs:string"/>
          </xs:sequence>
        </xs:complexType>
      </xs:element>
      <xs:element name="FullCountryInfo">
        <xs:complexType>
          <xs:sequence>
            <xs:element name="sCountryISOCode" type="xs:string"/>
          </xs:sequence>
        </xs:complexType>
      </xs:element>
      <xs:element name="FullCountryInfoResponse">
        <xs:complexType>
          <xs:sequence>
            <xs:element name="FullCountryInfoResult" type="tns:tCountryInfo"/>
          </xs:sequence>
        </xs:complexType>
      </xs:element>
      <xs:element name="FullCountryInfoAllCountries">
        <xs:complexType>
          <xs:sequence/>
        </xs:complexType>
      </xs:element>
      <xs:element name="FullCountryInfoAllCountriesResponse">
        <xs:complexType>
          <xs:sequence>
            <xs:element name="FullCountryInfoAllCountriesResult" type="tns:ArrayOftCountryInfo"/>
          </xs:sequence>
        </xs:complexType>
      </xs:element>
      <xs:element name="CountriesUsingCurrency">
        <xs:complexType>
          <xs:sequence>
            <xs:element name="sISOCurrencyCode" type="xs:string"/>
          </xs:sequence>
        </xs:complexType>
      </xs:element>
      <xs:element name="CountriesUsingCurrencyResponse">
        <xs:complexType>
          <xs:sequence>
            <xs:element name="CountriesUsingCurrencyResult" type="tns:ArrayOftCountryCodeAndName"/>
          </xs:sequence>
        </xs:complexType>
      </xs:element>
      <xs:element name="ListOfLanguagesByName">
        <xs:complexType>
          <xs:sequence/>
        </xs:complexType>
      </xs:element>
      <xs:element name="ListOfLanguagesByNameResponse">
        <xs:complexType>
          <xs:sequence>
            <xs:element name="ListOfLanguagesByNameResult" type="tns:ArrayOftLanguage"/>
          </xs:sequence>
        </xs:complexType>
      </xs:element>
      <xs:element name="ListOfLanguagesByCode">
        <xs:complexType>
          <xs:sequence/>
        </xs:complexType>
      </xs:element>
      <xs:element name="ListOfLanguagesByCodeResponse">
        <xs:complexType>
          <xs:sequence>
            <xs:element name="ListOfLanguagesByCodeResult" type="tns:ArrayOftLanguage"/>
          </xs:sequence>
        </xs:complexType>
      </xs:element>
      <xs:element name="LanguageName">
        <xs:complexType>
          <xs:sequence>
            <xs:element name="sISOCode" type="xs:string"/>
          </xs:sequence>
        </xs:complexType>
      </xs:element>
      <xs:element name="LanguageNameResponse">
        <xs:complexType>
          <xs:sequence>
            <xs:element name="LanguageNameResult" type="xs:string"/>
          </xs:sequence>
        </xs:complexType>
      </xs:element>
      <xs:element name="LanguageISOCode">
        <xs:complexType>
          <xs:sequence>
            <xs:element name="sLanguageName" type="xs:string"/>
          </xs:sequence>
        </xs:complexType>
      </xs:element>
      <xs:element name="LanguageISOCodeResponse">
        <xs:complexType>
          <xs:sequence>
            <xs:element name="LanguageISOCodeResult" type="xs:string"/>
          </xs:sequence>
        </xs:complexType>
      </xs:element>
    </xs:schema>
  </types>
  <message name="ListOfContinentsByNameSoapRequest">
    <part name="parameters" element="tns:ListOfContinentsByName"/>
  </message>
  <message name="ListOfContinentsByNameSoapResponse">
    <part name="parameters" element="tns:ListOfContinentsByNameResponse"/>
  </message>
  <message name="ListOfContinentsByCodeSoapRequest">
    <part name="parameters" element="tns:ListOfContinentsByCode"/>
  </message>
  <message name="ListOfContinentsByCodeSoapResponse">
    <part name="parameters" element="tns:ListOfContinentsByCodeResponse"/>
  </message>
  <message name="ListOfCurrenciesByNameSoapRequest">
    <part name="parameters" element="tns:ListOfCurrenciesByName"/>
  </message>
  <message name="ListOfCurrenciesByNameSoapResponse">
    <part name="parameters" element="tns:ListOfCurrenciesByNameResponse"/>
  </message>
  <message name="ListOfCurrenciesByCodeSoapRequest">
    <part name="parameters" element="tns:ListOfCurrenciesByCode"/>
  </message>
  <message name="ListOfCurrenciesByCodeSoapResponse">
    <part name="parameters" element="tns:ListOfCurrenciesByCodeResponse"/>
  </message>
  <message name="CurrencyNameSoapRequest">
    <part name="parameters" element="tns:CurrencyName"/>
  </message>
  <message name="CurrencyNameSoapResponse">
    <part name="parameters" element="tns:CurrencyNameResponse"/>
  </message>
  <message name="ListOfCountryNamesByCodeSoapRequest">
    <part name="parameters" element="tns:ListOfCountryNamesByCode"/>
  </message>
  <message name="ListOfCountryNamesByCodeSoapResponse">
    <part name="parameters" element="tns:ListOfCountryNamesByCodeResponse"/>
  </message>
  <message name="ListOfCountryNamesByNameSoapRequest">
    <part name="parameters" element="tns:ListOfCountryNamesByName"/>
  </message>
  <message name="ListOfCountryNamesByNameSoapResponse">
    <part name="parameters" element="tns:ListOfCountryNamesByNameResponse"/>
  </message>
  <message name="ListOfCountryNamesGroupedByContinentSoapRequest">
    <part name="parameters" element="tns:ListOfCountryNamesGroupedByContinent"/>
  </message>
  <message name="ListOfCountryNamesGroupedByContinentSoapResponse">
    <part name="parameters" element="tns:ListOfCountryNamesGroupedByContinentResponse"/>
  </message>
  <message name="CountryNameSoapRequest">
    <part name="parameters" element="tns:CountryName"/>
  </message>
  <message name="CountryNameSoapResponse">
    <part name="parameters" element="tns:CountryNameResponse"/>
  </message>
  <message name="CountryISOCodeSoapRequest">
    <part name="parameters" element="tns:CountryISOCode"/>
  </message>
  <message name="CountryISOCodeSoapResponse">
    <part name="parameters" element="tns:CountryISOCodeResponse"/>
  </message>
  <message name="CapitalCitySoapRequest">
    <part name="parameters" element="tns:CapitalCity"/>
  </message>
  <message name="CapitalCitySoapResponse">
    <part name="parameters" element="tns:CapitalCityResponse"/>
  </message>
  <message name="CountryCurrencySoapRequest">
    <part name="parameters" element="tns:CountryCurrency"/>
  </message>
  <message name="CountryCurrencySoapResponse">
    <part name="parameters" element="tns:CountryCurrencyResponse"/>
  </message>
  <message name="CountryFlagSoapRequest">
    <part name="parameters" element="tns:CountryFlag"/>
  </message>
  <message name="CountryFlagSoapResponse">
    <part name="parameters" element="tns:CountryFlagResponse"/>
  </message>
  <message name="CountryIntPhoneCodeSoapRequest">
    <part name="parameters" element="tns:CountryIntPhoneCode"/>
  </message>
  <message name="CountryIntPhoneCodeSoapResponse">
    <part name="parameters" element="tns:CountryIntPhoneCodeResponse"/>
  </message>
  <message name="FullCountryInfoSoapRequest">
    <part name="parameters" element="tns:FullCountryInfo"/>
  </message>
  <message name="FullCountryInfoSoapResponse">
    <part name="parameters" element="tns:FullCountryInfoResponse"/>
  </message>
  <message name="FullCountryInfoAllCountriesSoapRequest">
    <part name="parameters" element="tns:FullCountryInfoAllCountries"/>
  </message>
  <message name="FullCountryInfoAllCountriesSoapResponse">
    <part name="parameters" element="tns:FullCountryInfoAllCountriesResponse"/>
  </message>
  <message name="CountriesUsingCurrencySoapRequest">
    <part name="parameters" element="tns:CountriesUsingCurrency"/>
  </message>
  <message name="CountriesUsingCurrencySoapResponse">
    <part name="parameters" element="tns:CountriesUsingCurrencyResponse"/>
  </message>
  <message name="ListOfLanguagesByNameSoapRequest">
    <part name="parameters" element="tns:ListOfLanguagesByName"/>
  </message>
  <message name="ListOfLanguagesByNameSoapResponse">
    <part name="parameters" element="tns:ListOfLanguagesByNameResponse"/>
  </message>
  <message name="ListOfLanguagesByCodeSoapRequest">
    <part name="parameters" element="tns:ListOfLanguagesByCode"/>
  </message>
  <message name="ListOfLanguagesByCodeSoapResponse">
    <part name="parameters" element="tns:ListOfLanguagesByCodeResponse"/>
  </message>
  <message name="LanguageNameSoapRequest">
    <part name="parameters" element="tns:LanguageName"/>
  </message>
  <message name="LanguageNameSoapResponse">
    <part name="parameters" element="tns:LanguageNameResponse"/>
  </message>
  <message name="LanguageISOCodeSoapRequest">
    <part name="parameters" element="tns:LanguageISOCode"/>
  </message>
  <message name="LanguageISOCodeSoapResponse">
    <part name="parameters" element="tns:LanguageISOCodeResponse"/>
  </message>
  <portType name="CountryInfoServiceSoapType">
    <operation name="ListOfContinentsByName">
      <documentation>Returns a list of continents ordered by name.</documentation>
      <input message="tns:ListOfContinentsByNameSoapRequest"/>
      <output message="tns:ListOfContinentsByNameSoapResponse"/>
    </operation>
    <operation name="ListOfContinentsByCode">
      <documentation>Returns a list of continents ordered by code.</documentation>
      <input message="tns:ListOfContinentsByCodeSoapRequest"/>
      <output message="tns:ListOfContinentsByCodeSoapResponse"/>
    </operation>
    <operation name="ListOfCurrenciesByName">
      <documentation>Returns a list of currencies ordered by name.</documentation>
      <input message="tns:ListOfCurrenciesByNameSoapRequest"/>
      <output message="tns:ListOfCurrenciesByNameSoapResponse"/>
    </operation>
    <operation name="ListOfCurrenciesByCode">
      <documentation>Returns a list of currencies ordered by code.</documentation>
      <input message="tns:ListOfCurrenciesByCodeSoapRequest"/>
      <output message="tns:ListOfCurrenciesByCodeSoapResponse"/>
    </operation>
    <operation name="CurrencyName">
      <documentation>Returns the name of the currency (if found)</documentation>
      <input message="tns:CurrencyNameSoapRequest"/>
      <output message="tns:CurrencyNameSoapResponse"/>
    </operation>
    <operation name="ListOfCountryNamesByCode">
      <documentation>Returns a list of all stored counties ordered by ISO code</documentation>
      <input message="tns:ListOfCountryNamesByCodeSoapRequest"/>
      <output message="tns:ListOfCountryNamesByCodeSoapResponse"/>
    </operation>
    <operation name="ListOfCountryNamesByName">
      <documentation>Returns a list of all stored counties ordered by country name</documentation>
      <input message="tns:ListOfCountryNamesByNameSoapRequest"/>
      <output message="tns:ListOfCountryNamesByNameSoapResponse"/>
    </operation>
    <operation name="ListOfCountryNamesGroupedByContinent">
      <documentation>Returns a list of all stored counties grouped per continent</documentation>
      <input message="tns:ListOfCountryNamesGroupedByContinentSoapRequest"/>
      <output message="tns:ListOfCountryNamesGroupedByContinentSoapResponse"/>
    </operation>
    <operation name="CountryName">
      <documentation>Searches the database for a country by the passed ISO country code</documentation>
      <input message="tns:CountryNameSoapRequest"/>
      <output message="tns:CountryNameSoapResponse"/>
    </operation>
    <operation name="CountryISOCode">
      <documentation>This function tries to found a country based on the passed country name.</documentation>
      <input message="tns:CountryISOCodeSoapRequest"/>
      <output message="tns:CountryISOCodeSoapResponse"/>
    </operation>
    <operation name="CapitalCity">
      <documentation>Returns the  name of the captial city for the passed country code</documentation>
      <input message="tns:CapitalCitySoapRequest"/>
      <output message="tns:CapitalCitySoapResponse"/>
    </operation>
    <operation name="CountryCurrency">
      <documentation>Returns the currency ISO code and name for the passed country ISO code</documentation>
      <input message="tns:CountryCurrencySoapRequest"/>
      <output message="tns:CountryCurrencySoapResponse"/>
    </operation>
    <operation name="CountryFlag">
      <documentation>Returns a link to a picture of the country flag</documentation>
      <input message="tns:CountryFlagSoapRequest"/>
      <output message="tns:CountryFlagSoapResponse"/>
    </operation>
    <operation name="CountryIntPhoneCode">
      <documentation>Returns the internation phone code for the passed ISO country code</documentation>
      <input message="tns:CountryIntPhoneCodeSoapRequest"/>
      <output message="tns:CountryIntPhoneCodeSoapResponse"/>
    </operation>
    <operation name="FullCountryInfo">
      <documentation>Returns a struct with all the stored country information. Pass the ISO country code</documentation>
      <input message="tns:FullCountryInfoSoapRequest"/>
      <output message="tns:FullCountryInfoSoapResponse"/>
    </operation>
    <operation name="FullCountryInfoAllCountries">
      <documentation>Returns an array with all countries and all the language information stored</documentation>
      <input message="tns:FullCountryInfoAllCountriesSoapRequest"/>
      <output message="tns:FullCountryInfoAllCountriesSoapResponse"/>
    </operation>
    <operation name="CountriesUsingCurrency">
      <documentation>Returns a list of all countries that use the same currency code. Pass a ISO currency code</documentation>
      <input message="tns:CountriesUsingCurrencySoapRequest"/>
      <output message="tns:CountriesUsingCurrencySoapResponse"/>
    </operation>
    <operation name="ListOfLanguagesByName">
      <documentation>Returns an array of languages ordered by name</documentation>
      <input message="tns:ListOfLanguagesByNameSoapRequest"/>
      <output message="tns:ListOfLanguagesByNameSoapResponse"/>
    </operation>
    <operation name="ListOfLanguagesByCode">
      <documentation>Returns an array of languages ordered by code</documentation>
      <input message="tns:ListOfLanguagesByCodeSoapRequest"/>
      <output message="tns:ListOfLanguagesByCodeSoapResponse"/>
    </operation>
    <operation name="LanguageName">
      <documentation>Find a language name based on the passed ISO language code</documentation>
      <input message="tns:LanguageNameSoapRequest"/>
      <output message="tns:LanguageNameSoapResponse"/>
    </operation>
    <operation name="LanguageISOCode">
      <documentation>Find a language ISO code based on the passed language name</documentation>
      <input message="tns:LanguageISOCodeSoapRequest"/>
      <output message="tns:LanguageISOCodeSoapResponse"/>
    </operation>
  </portType>
  <binding name="CountryInfoServiceSoapBinding" type="tns:CountryInfoServiceSoapType">
    <soap:binding style="document" transport="http://schemas.xmlsoap.org/soap/http"/>
    <operation name="ListOfContinentsByName">
      <soap:operation soapAction="" style="document"/>
      <input>
        <soap:body use="literal"/>
      </input>
      <output>
        <soap:body use="literal"/>
      </output>
    </operation>
    <operation name="ListOfContinentsByCode">
      <soap:operation soapAction="" style="document"/>
      <input>
        <soap:body use="literal"/>
      </input>
      <output>
        <soap:body use="literal"/>
      </output>
    </operation>
    <operation name="ListOfCurrenciesByName">
      <soap:operation soapAction="" style="document"/>
      <input>
        <soap:body use="literal"/>
      </input>
      <output>
        <soap:body use="literal"/>
      </output>
    </operation>
    <operation name="ListOfCurrenciesByCode">
      <soap:operation soapAction="" style="document"/>
      <input>
        <soap:body use="literal"/>
      </input>
      <output>
        <soap:body use="literal"/>
      </output>
    </operation>
    <operation name="CurrencyName">
      <soap:operation soapAction="" style="document"/>
      <input>
        <soap:body use="literal"/>
      </input>
      <output>
        <soap:body use="literal"/>
      </output>
    </operation>
    <operation name="ListOfCountryNamesByCode">
      <soap:operation soapAction="" style="document"/>
      <input>
        <soap:body use="literal"/>
      </input>
      <output>
        <soap:body use="literal"/>
      </output>
    </operation>
    <operation name="ListOfCountryNamesByName">
      <soap:operation soapAction="" style="document"/>
      <input>
        <soap:body use="literal"/>
      </input>
      <output>
        <soap:body use="literal"/>
      </output>
    </operation>
    <operation name="ListOfCountryNamesGroupedByContinent">
      <soap:operation soapAction="" style="document"/>
      <input>
        <soap:body use="literal"/>
      </input>
      <output>
        <soap:body use="literal"/>
      </output>
    </operation>
    <operation name="CountryName">
      <soap:operation soapAction="" style="document"/>
      <input>
        <soap:body use="literal"/>
      </input>
      <output>
        <soap:body use="literal"/>
      </output>
    </operation>
    <operation name="CountryISOCode">
      <soap:operation soapAction="" style="document"/>
      <input>
        <soap:body use="literal"/>
      </input>
      <output>
        <soap:body use="literal"/>
      </output>
    </operation>
    <operation name="CapitalCity">
      <soap:operation soapAction="" style="document"/>
      <input>
        <soap:body use="literal"/>
      </input>
      <output>
        <soap:body use="literal"/>
      </output>
    </operation>
    <operation name="CountryCurrency">
      <soap:operation soapAction="" style="document"/>
      <input>
        <soap:body use="literal"/>
      </input>
      <output>
        <soap:body use="literal"/>
      </output>
    </operation>
    <operation name="CountryFlag">
      <soap:operation soapAction="" style="document"/>
      <input>
        <soap:body use="literal"/>
      </input>
      <output>
        <soap:body use="literal"/>
      </output>
    </operation>
    <operation name="CountryIntPhoneCode">
      <soap:operation soapAction="" style="document"/>
      <input>
        <soap:body use="literal"/>
      </input>
      <output>
        <soap:body use="literal"/>
      </output>
    </operation>
    <operation name="FullCountryInfo">
      <soap:operation soapAction="" style="document"/>
      <input>
        <soap:body use="literal"/>
      </input>
      <output>
        <soap:body use="literal"/>
      </output>
    </operation>
    <operation name="FullCountryInfoAllCountries">
      <soap:operation soapAction="" style="document"/>
      <input>
        <soap:body use="literal"/>
      </input>
      <output>
        <soap:body use="literal"/>
      </output>
    </operation>
    <operation name="CountriesUsingCurrency">
      <soap:operation soapAction="" style="document"/>
      <input>
        <soap:body use="literal"/>
      </input>
      <output>
        <soap:body use="literal"/>
      </output>
    </operation>
    <operation name="ListOfLanguagesByName">
      <soap:operation soapAction="" style="document"/>
      <input>
        <soap:body use="literal"/>
      </input>
      <output>
        <soap:body use="literal"/>
      </output>
    </operation>
    <operation name="ListOfLanguagesByCode">
      <soap:operation soapAction="" style="document"/>
      <input>
        <soap:body use="literal"/>
      </input>
      <output>
        <soap:body use="literal"/>
      </output>
    </operation>
    <operation name="LanguageName">
      <soap:operation soapAction="" style="document"/>
      <input>
        <soap:body use="literal"/>
      </input>
      <output>
        <soap:body use="literal"/>
      </output>
    </operation>
    <operation name="LanguageISOCode">
      <soap:operation soapAction="" style="document"/>
      <input>
        <soap:body use="literal"/>
      </input>
      <output>
        <soap:body use="literal"/>
      </output>
    </operation>
  </binding>
  <binding name="CountryInfoServiceSoapBinding12" type="tns:CountryInfoServiceSoapType">
    <soap12:binding style="document" transport="http://schemas.xmlsoap.org/soap/http"/>
    <operation name="ListOfContinentsByName">
      <soap12:operation soapAction="" style="document"/>
      <input>
        <soap12:body use="literal"/>
      </input>
      <output>
        <soap12:body use="literal"/>
      </output>
    </operation>
    <operation name="ListOfContinentsByCode">
      <soap12:operation soapAction="" style="document"/>
      <input>
        <soap12:body use="literal"/>
      </input>
      <output>
        <soap12:body use="literal"/>
      </output>
    </operation>
    <operation name="ListOfCurrenciesByName">
      <soap12:operation soapAction="" style="document"/>
      <input>
        <soap12:body use="literal"/>
      </input>
      <output>
        <soap12:body use="literal"/>
      </output>
    </operation>
    <operation name="ListOfCurrenciesByCode">
      <soap12:operation soapAction="" style="document"/>
      <input>
        <soap12:body use="literal"/>
      </input>
      <output>
        <soap12:body use="literal"/>
      </output>
    </operation>
    <operation name="CurrencyName">
      <soap12:operation soapAction="" style="document"/>
      <input>
        <soap12:body use="literal"/>
      </input>
      <output>
        <soap12:body use="literal"/>
      </output>
    </operation>
    <operation name="ListOfCountryNamesByCode">
      <soap12:operation soapAction="" style="document"/>
      <input>
        <soap12:body use="literal"/>
      </input>
      <output>
        <soap12:body use="literal"/>
      </output>
    </operation>
    <operation name="ListOfCountryNamesByName">
      <soap12:operation soapAction="" style="document"/>
      <input>
        <soap12:body use="literal"/>
      </input>
      <output>
        <soap12:body use="literal"/>
      </output>
    </operation>
    <operation name="ListOfCountryNamesGroupedByContinent">
      <soap12:operation soapAction="" style="document"/>
      <input>
        <soap12:body use="literal"/>
      </input>
      <output>
        <soap12:body use="literal"/>
      </output>
    </operation>
    <operation name="CountryName">
      <soap12:operation soapAction="" style="document"/>
      <input>
        <soap12:body use="literal"/>
      </input>
      <output>
        <soap12:body use="literal"/>
      </output>
    </operation>
    <operation name="CountryISOCode">
      <soap12:operation soapAction="" style="document"/>
      <input>
        <soap12:body use="literal"/>
      </input>
      <output>
        <soap12:body use="literal"/>
      </output>
    </operation>
    <operation name="CapitalCity">
      <soap12:operation soapAction="" style="document"/>
      <input>
        <soap12:body use="literal"/>
      </input>
      <output>
        <soap12:body use="literal"/>
      </output>
    </operation>
    <operation name="CountryCurrency">
      <soap12:operation soapAction="" style="document"/>
      <input>
        <soap12:body use="literal"/>
      </input>
      <output>
        <soap12:body use="literal"/>
      </output>
    </operation>
    <operation name="CountryFlag">
      <soap12:operation soapAction="" style="document"/>
      <input>
        <soap12:body use="literal"/>
      </input>
      <output>
        <soap12:body use="literal"/>
      </output>
    </operation>
    <operation name="CountryIntPhoneCode">
      <soap12:operation soapAction="" style="document"/>
      <input>
        <soap12:body use="literal"/>
      </input>
      <output>
        <soap12:body use="literal"/>
      </output>
    </operation>
    <operation name="FullCountryInfo">
      <soap12:operation soapAction="" style="document"/>
      <input>
        <soap12:body use="literal"/>
      </input>
      <output>
        <soap12:body use="literal"/>
      </output>
    </operation>
    <operation name="FullCountryInfoAllCountries">
      <soap12:operation soapAction="" style="document"/>
      <input>
        <soap12:body use="literal"/>
      </input>
      <output>
        <soap12:body use="literal"/>
      </output>
    </operation>
    <operation name="CountriesUsingCurrency">
      <soap12:operation soapAction="" style="document"/>
      <input>
        <soap12:body use="literal"/>
      </input>
      <output>
        <soap12:body use="literal"/>
      </output>
    </operation>
    <operation name="ListOfLanguagesByName">
      <soap12:operation soapAction="" style="document"/>
      <input>
        <soap12:body use="literal"/>
      </input>
      <output>
        <soap12:body use="literal"/>
      </output>
    </operation>
    <operation name="ListOfLanguagesByCode">
      <soap12:operation soapAction="" style="document"/>
      <input>
        <soap12:body use="literal"/>
      </input>
      <output>
        <soap12:body use="literal"/>
      </output>
    </operation>
    <operation name="LanguageName">
      <soap12:operation soapAction="" style="document"/>
      <input>
        <soap12:body use="literal"/>
      </input>
      <output>
        <soap12:body use="literal"/>
      </output>
    </operation>
    <operation name="LanguageISOCode">
      <soap12:operation soapAction="" style="document"/>
      <input>
        <soap12:body use="literal"/>
      </input>
      <output>
        <soap12:body use="literal"/>
      </output>
    </operation>
  </binding>
  <service name="CountryInfoService">
    <documentation>This DataFlex Web Service opens up country information. 2 letter ISO codes are used for Country code. There are functions to retrieve the used Currency, Language, Capital City, Continent and Telephone code.</documentation>
    <port name="CountryInfoServiceSoap" binding="tns:CountryInfoServiceSoapBinding">
      <soap:address location="http://webservices.oorsprong.org/websamples.countryinfo/CountryInfoService.wso"/>
    </port>
    <port name="CountryInfoServiceSoap12" binding="tns:CountryInfoServiceSoapBinding12">
      <soap12:address location="http://webservices.oorsprong.org/websamples.countryinfo/CountryInfoService.wso"/>
    </port>
  </service>
</definitions>]]></con:content><con:type>http://schemas.xmlsoap.org/wsdl/</con:type></con:part></con:definitionCache><con:endpoints><con:endpoint>http://webservices.oorsprong.org/websamples.countryinfo/CountryInfoService.wso</con:endpoint></con:endpoints><con:operation id="4de4656a-4578-4b1d-a99b-2297b9cdc8c9" isOneWay="false" action="" name="CapitalCity" bindingOperationName="CapitalCity" type="Request-Response" inputName="" receivesAttachments="false" sendsAttachments="false" anonymous="optional"><con:settings/><con:call id="478b62bf-a135-4b57-b525-1edad3399291" name="Request 1"><con:settings/><con:encoding>UTF-8</con:encoding><con:endpoint>http://webservices.oorsprong.org/websamples.countryinfo/CountryInfoService.wso</con:endpoint><con:request><![CDATA[<soapenv:Envelope xmlns:soapenv="http://schemas.xmlsoap.org/soap/envelope/" xmlns:web="http://www.oorsprong.org/websamples.countryinfo">\r
   <soapenv:Header/>\r
   <soapenv:Body>\r
      <web:CapitalCity>\r
         <web:sCountryISOCode>?</web:sCountryISOCode>\r
      </web:CapitalCity>\r
   </soapenv:Body>\r
</soapenv:Envelope>]]></con:request><con:wsaConfig mustUnderstand="NONE" version="200508" action="http://www.oorsprong.org/websamples.countryinfo/CountryInfoServiceSoapType/CapitalCityRequest"/></con:call></con:operation><con:operation id="9b3fcd2b-e192-4c99-8348-a96c49c92a02" isOneWay="false" action="" name="CountriesUsingCurrency" bindingOperationName="CountriesUsingCurrency" type="Request-Response" inputName="" receivesAttachments="false" sendsAttachments="false" anonymous="optional"><con:settings/><con:call id="196cc063-9ab5-4103-8347-7a5c61de663d" name="Request 1"><con:settings/><con:encoding>UTF-8</con:encoding><con:endpoint>http://webservices.oorsprong.org/websamples.countryinfo/CountryInfoService.wso</con:endpoint><con:request><![CDATA[<soapenv:Envelope xmlns:soapenv="http://schemas.xmlsoap.org/soap/envelope/" xmlns:web="http://www.oorsprong.org/websamples.countryinfo">\r
   <soapenv:Header/>\r
   <soapenv:Body>\r
      <web:CountriesUsingCurrency>\r
         <web:sISOCurrencyCode>?</web:sISOCurrencyCode>\r
      </web:CountriesUsingCurrency>\r
   </soapenv:Body>\r
</soapenv:Envelope>]]></con:request><con:wsaConfig mustUnderstand="NONE" version="200508" action="http://www.oorsprong.org/websamples.countryinfo/CountryInfoServiceSoapType/CountriesUsingCurrencyRequest"/></con:call></con:operation><con:operation id="d3639bbf-c978-4d47-abb7-98f0b233a0ec" isOneWay="false" action="" name="CountryCurrency" bindingOperationName="CountryCurrency" type="Request-Response" inputName="" receivesAttachments="false" sendsAttachments="false" anonymous="optional"><con:settings/><con:call id="68711fe8-18dd-4296-9a45-9184d0017cde" name="Request 1"><con:settings/><con:encoding>UTF-8</con:encoding><con:endpoint>http://webservices.oorsprong.org/websamples.countryinfo/CountryInfoService.wso</con:endpoint><con:request><![CDATA[<soapenv:Envelope xmlns:soapenv="http://schemas.xmlsoap.org/soap/envelope/" xmlns:web="http://www.oorsprong.org/websamples.countryinfo">\r
   <soapenv:Header/>\r
   <soapenv:Body>\r
      <web:CountryCurrency>\r
         <web:sCountryISOCode>?</web:sCountryISOCode>\r
      </web:CountryCurrency>\r
   </soapenv:Body>\r
</soapenv:Envelope>]]></con:request><con:wsaConfig mustUnderstand="NONE" version="200508" action="http://www.oorsprong.org/websamples.countryinfo/CountryInfoServiceSoapType/CountryCurrencyRequest"/></con:call></con:operation><con:operation id="974a8e0c-105c-4f7b-8101-3d3a01f44f83" isOneWay="false" action="" name="CountryFlag" bindingOperationName="CountryFlag" type="Request-Response" inputName="" receivesAttachments="false" sendsAttachments="false" anonymous="optional"><con:settings/><con:call id="64542e86-c4be-4084-84e7-5df4a0f15053" name="Request 1"><con:settings/><con:encoding>UTF-8</con:encoding><con:endpoint>http://webservices.oorsprong.org/websamples.countryinfo/CountryInfoService.wso</con:endpoint><con:request><![CDATA[<soapenv:Envelope xmlns:soapenv="http://schemas.xmlsoap.org/soap/envelope/" xmlns:web="http://www.oorsprong.org/websamples.countryinfo">\r
   <soapenv:Header/>\r
   <soapenv:Body>\r
      <web:CountryFlag>\r
         <web:sCountryISOCode>?</web:sCountryISOCode>\r
      </web:CountryFlag>\r
   </soapenv:Body>\r
</soapenv:Envelope>]]></con:request><con:wsaConfig mustUnderstand="NONE" version="200508" action="http://www.oorsprong.org/websamples.countryinfo/CountryInfoServiceSoapType/CountryFlagRequest"/></con:call></con:operation><con:operation id="52d6d72e-1d1f-4d71-858c-d0795ffee329" isOneWay="false" action="" name="CountryIntPhoneCode" bindingOperationName="CountryIntPhoneCode" type="Request-Response" inputName="" receivesAttachments="false" sendsAttachments="false" anonymous="optional"><con:settings/><con:call id="201c29de-0f88-4bfa-9497-44e3af7a564e" name="Request 1"><con:settings/><con:encoding>UTF-8</con:encoding><con:endpoint>http://webservices.oorsprong.org/websamples.countryinfo/CountryInfoService.wso</con:endpoint><con:request><![CDATA[<soapenv:Envelope xmlns:soapenv="http://schemas.xmlsoap.org/soap/envelope/" xmlns:web="http://www.oorsprong.org/websamples.countryinfo">\r
   <soapenv:Header/>\r
   <soapenv:Body>\r
      <web:CountryIntPhoneCode>\r
         <web:sCountryISOCode>?</web:sCountryISOCode>\r
      </web:CountryIntPhoneCode>\r
   </soapenv:Body>\r
</soapenv:Envelope>]]></con:request><con:wsaConfig mustUnderstand="NONE" version="200508" action="http://www.oorsprong.org/websamples.countryinfo/CountryInfoServiceSoapType/CountryIntPhoneCodeRequest"/></con:call></con:operation><con:operation id="1a6bb301-4c64-4587-9777-beaa6f37c3c3" isOneWay="false" action="" name="CountryISOCode" bindingOperationName="CountryISOCode" type="Request-Response" inputName="" receivesAttachments="false" sendsAttachments="false" anonymous="optional"><con:settings/><con:call id="f41004a1-4092-44aa-958d-d2d91d79c82a" name="Request 1"><con:settings/><con:encoding>UTF-8</con:encoding><con:endpoint>http://webservices.oorsprong.org/websamples.countryinfo/CountryInfoService.wso</con:endpoint><con:request><![CDATA[<soapenv:Envelope xmlns:soapenv="http://schemas.xmlsoap.org/soap/envelope/" xmlns:web="http://www.oorsprong.org/websamples.countryinfo">\r
   <soapenv:Header/>\r
   <soapenv:Body>\r
      <web:CountryISOCode>\r
         <web:sCountryName>?</web:sCountryName>\r
      </web:CountryISOCode>\r
   </soapenv:Body>\r
</soapenv:Envelope>]]></con:request><con:wsaConfig mustUnderstand="NONE" version="200508" action="http://www.oorsprong.org/websamples.countryinfo/CountryInfoServiceSoapType/CountryISOCodeRequest"/></con:call></con:operation><con:operation id="29ae5954-909a-4610-a078-655440b93738" isOneWay="false" action="" name="CountryName" bindingOperationName="CountryName" type="Request-Response" inputName="" receivesAttachments="false" sendsAttachments="false" anonymous="optional"><con:settings/><con:call id="d951ba00-f3f1-4211-b678-87dfbb97a742" name="Request 1"><con:settings/><con:encoding>UTF-8</con:encoding><con:endpoint>http://webservices.oorsprong.org/websamples.countryinfo/CountryInfoService.wso</con:endpoint><con:request><![CDATA[<soapenv:Envelope xmlns:soapenv="http://schemas.xmlsoap.org/soap/envelope/" xmlns:web="http://www.oorsprong.org/websamples.countryinfo">\r
   <soapenv:Header/>\r
   <soapenv:Body>\r
      <web:CountryName>\r
         <web:sCountryISOCode>?</web:sCountryISOCode>\r
      </web:CountryName>\r
   </soapenv:Body>\r
</soapenv:Envelope>]]></con:request><con:wsaConfig mustUnderstand="NONE" version="200508" action="http://www.oorsprong.org/websamples.countryinfo/CountryInfoServiceSoapType/CountryNameRequest"/></con:call></con:operation><con:operation id="5e3bc4e6-27ba-4176-8a04-db2f1a026870" isOneWay="false" action="" name="CurrencyName" bindingOperationName="CurrencyName" type="Request-Response" inputName="" receivesAttachments="false" sendsAttachments="false" anonymous="optional"><con:settings/><con:call id="89021c9e-4e21-48f7-8912-bf76db22ab26" name="Request 1"><con:settings/><con:encoding>UTF-8</con:encoding><con:endpoint>http://webservices.oorsprong.org/websamples.countryinfo/CountryInfoService.wso</con:endpoint><con:request><![CDATA[<soapenv:Envelope xmlns:soapenv="http://schemas.xmlsoap.org/soap/envelope/" xmlns:web="http://www.oorsprong.org/websamples.countryinfo">\r
   <soapenv:Header/>\r
   <soapenv:Body>\r
      <web:CurrencyName>\r
         <web:sCurrencyISOCode>?</web:sCurrencyISOCode>\r
      </web:CurrencyName>\r
   </soapenv:Body>\r
</soapenv:Envelope>]]></con:request><con:wsaConfig mustUnderstand="NONE" version="200508" action="http://www.oorsprong.org/websamples.countryinfo/CountryInfoServiceSoapType/CurrencyNameRequest"/></con:call></con:operation><con:operation id="6156af8b-1d6e-4cf0-9aff-a9d3345e44a7" isOneWay="false" action="" name="FullCountryInfo" bindingOperationName="FullCountryInfo" type="Request-Response" inputName="" receivesAttachments="false" sendsAttachments="false" anonymous="optional"><con:settings/><con:call id="e8173296-08ae-4427-882a-fb6fd4d07a72" name="Request 1"><con:settings/><con:encoding>UTF-8</con:encoding><con:endpoint>http://webservices.oorsprong.org/websamples.countryinfo/CountryInfoService.wso</con:endpoint><con:request><![CDATA[<soapenv:Envelope xmlns:soapenv="http://schemas.xmlsoap.org/soap/envelope/" xmlns:web="http://www.oorsprong.org/websamples.countryinfo">\r
   <soapenv:Header/>\r
   <soapenv:Body>\r
      <web:FullCountryInfo>\r
         <web:sCountryISOCode>?</web:sCountryISOCode>\r
      </web:FullCountryInfo>\r
   </soapenv:Body>\r
</soapenv:Envelope>]]></con:request><con:wsaConfig mustUnderstand="NONE" version="200508" action="http://www.oorsprong.org/websamples.countryinfo/CountryInfoServiceSoapType/FullCountryInfoRequest"/></con:call></con:operation><con:operation id="366e85ef-881e-4acb-adb2-906d2f297f80" isOneWay="false" action="" name="FullCountryInfoAllCountries" bindingOperationName="FullCountryInfoAllCountries" type="Request-Response" inputName="" receivesAttachments="false" sendsAttachments="false" anonymous="optional"><con:settings/><con:call id="23c31413-6904-437a-b98c-79ae0569d018" name="Request 1"><con:settings/><con:encoding>UTF-8</con:encoding><con:endpoint>http://webservices.oorsprong.org/websamples.countryinfo/CountryInfoService.wso</con:endpoint><con:request><![CDATA[<soapenv:Envelope xmlns:soapenv="http://schemas.xmlsoap.org/soap/envelope/" xmlns:web="http://www.oorsprong.org/websamples.countryinfo">\r
   <soapenv:Header/>\r
   <soapenv:Body>\r
      <web:FullCountryInfoAllCountries/>\r
   </soapenv:Body>\r
</soapenv:Envelope>]]></con:request><con:wsaConfig mustUnderstand="NONE" version="200508" action="http://www.oorsprong.org/websamples.countryinfo/CountryInfoServiceSoapType/FullCountryInfoAllCountriesRequest"/></con:call></con:operation><con:operation id="80c1e16a-841c-4040-b998-66a2e1443f86" isOneWay="false" action="" name="LanguageISOCode" bindingOperationName="LanguageISOCode" type="Request-Response" inputName="" receivesAttachments="false" sendsAttachments="false" anonymous="optional"><con:settings/><con:call id="c2a84d35-799c-4f0a-8310-54dbfe0f3c53" name="Request 1"><con:settings/><con:encoding>UTF-8</con:encoding><con:endpoint>http://webservices.oorsprong.org/websamples.countryinfo/CountryInfoService.wso</con:endpoint><con:request><![CDATA[<soapenv:Envelope xmlns:soapenv="http://schemas.xmlsoap.org/soap/envelope/" xmlns:web="http://www.oorsprong.org/websamples.countryinfo">\r
   <soapenv:Header/>\r
   <soapenv:Body>\r
      <web:LanguageISOCode>\r
         <web:sLanguageName>?</web:sLanguageName>\r
      </web:LanguageISOCode>\r
   </soapenv:Body>\r
</soapenv:Envelope>]]></con:request><con:wsaConfig mustUnderstand="NONE" version="200508" action="http://www.oorsprong.org/websamples.countryinfo/CountryInfoServiceSoapType/LanguageISOCodeRequest"/></con:call></con:operation><con:operation id="41d244ef-879d-4b52-83f1-7a0ff4585c83" isOneWay="false" action="" name="LanguageName" bindingOperationName="LanguageName" type="Request-Response" inputName="" receivesAttachments="false" sendsAttachments="false" anonymous="optional"><con:settings/><con:call id="a642df5e-6853-4c3e-9bb7-0e11c3599d0c" name="Request 1"><con:settings/><con:encoding>UTF-8</con:encoding><con:endpoint>http://webservices.oorsprong.org/websamples.countryinfo/CountryInfoService.wso</con:endpoint><con:request><![CDATA[<soapenv:Envelope xmlns:soapenv="http://schemas.xmlsoap.org/soap/envelope/" xmlns:web="http://www.oorsprong.org/websamples.countryinfo">\r
   <soapenv:Header/>\r
   <soapenv:Body>\r
      <web:LanguageName>\r
         <web:sISOCode>?</web:sISOCode>\r
      </web:LanguageName>\r
   </soapenv:Body>\r
</soapenv:Envelope>]]></con:request><con:wsaConfig mustUnderstand="NONE" version="200508" action="http://www.oorsprong.org/websamples.countryinfo/CountryInfoServiceSoapType/LanguageNameRequest"/></con:call></con:operation><con:operation id="7f20ce9a-b324-46fc-a2c4-c5e9c5852d0b" isOneWay="false" action="" name="ListOfContinentsByCode" bindingOperationName="ListOfContinentsByCode" type="Request-Response" inputName="" receivesAttachments="false" sendsAttachments="false" anonymous="optional"><con:settings/><con:call id="455c275b-26a9-486f-9749-a3a4062533c7" name="Request 1"><con:settings/><con:encoding>UTF-8</con:encoding><con:endpoint>http://webservices.oorsprong.org/websamples.countryinfo/CountryInfoService.wso</con:endpoint><con:request><![CDATA[<soapenv:Envelope xmlns:soapenv="http://schemas.xmlsoap.org/soap/envelope/" xmlns:web="http://www.oorsprong.org/websamples.countryinfo">\r
   <soapenv:Header/>\r
   <soapenv:Body>\r
      <web:ListOfContinentsByCode/>\r
   </soapenv:Body>\r
</soapenv:Envelope>]]></con:request><con:wsaConfig mustUnderstand="NONE" version="200508" action="http://www.oorsprong.org/websamples.countryinfo/CountryInfoServiceSoapType/ListOfContinentsByCodeRequest"/></con:call></con:operation><con:operation id="5cd744c6-18ef-4677-9e59-41188e74488b" isOneWay="false" action="" name="ListOfContinentsByName" bindingOperationName="ListOfContinentsByName" type="Request-Response" inputName="" receivesAttachments="false" sendsAttachments="false" anonymous="optional"><con:settings/><con:call id="cf6812ff-aef5-4d8d-83a6-d011a6849a49" name="Request 1"><con:settings/><con:encoding>UTF-8</con:encoding><con:endpoint>http://webservices.oorsprong.org/websamples.countryinfo/CountryInfoService.wso</con:endpoint><con:request><![CDATA[<soapenv:Envelope xmlns:soapenv="http://schemas.xmlsoap.org/soap/envelope/" xmlns:web="http://www.oorsprong.org/websamples.countryinfo">\r
   <soapenv:Header/>\r
   <soapenv:Body>\r
      <web:ListOfContinentsByName/>\r
   </soapenv:Body>\r
</soapenv:Envelope>]]></con:request><con:wsaConfig mustUnderstand="NONE" version="200508" action="http://www.oorsprong.org/websamples.countryinfo/CountryInfoServiceSoapType/ListOfContinentsByNameRequest"/></con:call></con:operation><con:operation id="24bb0f8f-ed07-4ed3-8d69-754be71722d2" isOneWay="false" action="" name="ListOfCountryNamesByCode" bindingOperationName="ListOfCountryNamesByCode" type="Request-Response" inputName="" receivesAttachments="false" sendsAttachments="false" anonymous="optional"><con:settings/><con:call id="26fefad3-2799-4332-b9f6-cba1035b6f0c" name="Request 1"><con:settings/><con:encoding>UTF-8</con:encoding><con:endpoint>http://webservices.oorsprong.org/websamples.countryinfo/CountryInfoService.wso</con:endpoint><con:request><![CDATA[<soapenv:Envelope xmlns:soapenv="http://schemas.xmlsoap.org/soap/envelope/" xmlns:web="http://www.oorsprong.org/websamples.countryinfo">\r
   <soapenv:Header/>\r
   <soapenv:Body>\r
      <web:ListOfCountryNamesByCode/>\r
   </soapenv:Body>\r
</soapenv:Envelope>]]></con:request><con:wsaConfig mustUnderstand="NONE" version="200508" action="http://www.oorsprong.org/websamples.countryinfo/CountryInfoServiceSoapType/ListOfCountryNamesByCodeRequest"/></con:call></con:operation><con:operation id="d0dc720d-d4e6-4e3c-9bde-68c72499b85e" isOneWay="false" action="" name="ListOfCountryNamesByName" bindingOperationName="ListOfCountryNamesByName" type="Request-Response" inputName="" receivesAttachments="false" sendsAttachments="false" anonymous="optional"><con:settings/><con:call id="3d0068e8-3df8-45a4-9d23-a5c93b1338cc" name="Request 1"><con:settings/><con:encoding>UTF-8</con:encoding><con:endpoint>http://webservices.oorsprong.org/websamples.countryinfo/CountryInfoService.wso</con:endpoint><con:request><![CDATA[<soapenv:Envelope xmlns:soapenv="http://schemas.xmlsoap.org/soap/envelope/" xmlns:web="http://www.oorsprong.org/websamples.countryinfo">\r
   <soapenv:Header/>\r
   <soapenv:Body>\r
      <web:ListOfCountryNamesByName/>\r
   </soapenv:Body>\r
</soapenv:Envelope>]]></con:request><con:wsaConfig mustUnderstand="NONE" version="200508" action="http://www.oorsprong.org/websamples.countryinfo/CountryInfoServiceSoapType/ListOfCountryNamesByNameRequest"/></con:call></con:operation><con:operation id="4dc0eef4-237a-463e-acfe-2c89e4852e6f" isOneWay="false" action="" name="ListOfCountryNamesGroupedByContinent" bindingOperationName="ListOfCountryNamesGroupedByContinent" type="Request-Response" inputName="" receivesAttachments="false" sendsAttachments="false" anonymous="optional"><con:settings/><con:call id="ecb51974-8b9b-4f90-a469-4c8682d87246" name="Request 1"><con:settings/><con:encoding>UTF-8</con:encoding><con:endpoint>http://webservices.oorsprong.org/websamples.countryinfo/CountryInfoService.wso</con:endpoint><con:request><![CDATA[<soapenv:Envelope xmlns:soapenv="http://schemas.xmlsoap.org/soap/envelope/" xmlns:web="http://www.oorsprong.org/websamples.countryinfo">\r
   <soapenv:Header/>\r
   <soapenv:Body>\r
      <web:ListOfCountryNamesGroupedByContinent/>\r
   </soapenv:Body>\r
</soapenv:Envelope>]]></con:request><con:wsaConfig mustUnderstand="NONE" version="200508" action="http://www.oorsprong.org/websamples.countryinfo/CountryInfoServiceSoapType/ListOfCountryNamesGroupedByContinentRequest"/></con:call></con:operation><con:operation id="57efa531-a9c7-4dc0-b583-83bfde05f90d" isOneWay="false" action="" name="ListOfCurrenciesByCode" bindingOperationName="ListOfCurrenciesByCode" type="Request-Response" inputName="" receivesAttachments="false" sendsAttachments="false" anonymous="optional"><con:settings/><con:call id="0a8d98a1-4c5f-4b43-9c07-0e85d04ed261" name="Request 1"><con:settings/><con:encoding>UTF-8</con:encoding><con:endpoint>http://webservices.oorsprong.org/websamples.countryinfo/CountryInfoService.wso</con:endpoint><con:request><![CDATA[<soapenv:Envelope xmlns:soapenv="http://schemas.xmlsoap.org/soap/envelope/" xmlns:web="http://www.oorsprong.org/websamples.countryinfo">\r
   <soapenv:Header/>\r
   <soapenv:Body>\r
      <web:ListOfCurrenciesByCode/>\r
   </soapenv:Body>\r
</soapenv:Envelope>]]></con:request><con:wsaConfig mustUnderstand="NONE" version="200508" action="http://www.oorsprong.org/websamples.countryinfo/CountryInfoServiceSoapType/ListOfCurrenciesByCodeRequest"/></con:call></con:operation><con:operation id="c0600b9a-304a-4701-bf12-562f0692344e" isOneWay="false" action="" name="ListOfCurrenciesByName" bindingOperationName="ListOfCurrenciesByName" type="Request-Response" inputName="" receivesAttachments="false" sendsAttachments="false" anonymous="optional"><con:settings/><con:call id="f3c7e440-be73-4939-8ae4-e52e90360c43" name="Request 1"><con:settings/><con:encoding>UTF-8</con:encoding><con:endpoint>http://webservices.oorsprong.org/websamples.countryinfo/CountryInfoService.wso</con:endpoint><con:request><![CDATA[<soapenv:Envelope xmlns:soapenv="http://schemas.xmlsoap.org/soap/envelope/" xmlns:web="http://www.oorsprong.org/websamples.countryinfo">\r
   <soapenv:Header/>\r
   <soapenv:Body>\r
      <web:ListOfCurrenciesByName/>\r
   </soapenv:Body>\r
</soapenv:Envelope>]]></con:request><con:wsaConfig mustUnderstand="NONE" version="200508" action="http://www.oorsprong.org/websamples.countryinfo/CountryInfoServiceSoapType/ListOfCurrenciesByNameRequest"/></con:call></con:operation><con:operation id="9d3727b1-10cb-41ec-ba09-367a709c54e6" isOneWay="false" action="" name="ListOfLanguagesByCode" bindingOperationName="ListOfLanguagesByCode" type="Request-Response" inputName="" receivesAttachments="false" sendsAttachments="false" anonymous="optional"><con:settings/><con:call id="c2ff76eb-1089-4ce6-ace1-a26256e09dec" name="Request 1"><con:settings/><con:encoding>UTF-8</con:encoding><con:endpoint>http://webservices.oorsprong.org/websamples.countryinfo/CountryInfoService.wso</con:endpoint><con:request><![CDATA[<soapenv:Envelope xmlns:soapenv="http://schemas.xmlsoap.org/soap/envelope/" xmlns:web="http://www.oorsprong.org/websamples.countryinfo">\r
   <soapenv:Header/>\r
   <soapenv:Body>\r
      <web:ListOfLanguagesByCode/>\r
   </soapenv:Body>\r
</soapenv:Envelope>]]></con:request><con:wsaConfig mustUnderstand="NONE" version="200508" action="http://www.oorsprong.org/websamples.countryinfo/CountryInfoServiceSoapType/ListOfLanguagesByCodeRequest"/></con:call></con:operation><con:operation id="472004b5-8860-47ee-ad0c-699b63cf5677" isOneWay="false" action="" name="ListOfLanguagesByName" bindingOperationName="ListOfLanguagesByName" type="Request-Response" inputName="" receivesAttachments="false" sendsAttachments="false" anonymous="optional"><con:settings/><con:call id="c5c7b2c0-3cea-4a71-badf-37c7ef690516" name="Request 1"><con:settings/><con:encoding>UTF-8</con:encoding><con:endpoint>http://webservices.oorsprong.org/websamples.countryinfo/CountryInfoService.wso</con:endpoint><con:request><![CDATA[<soapenv:Envelope xmlns:soapenv="http://schemas.xmlsoap.org/soap/envelope/" xmlns:web="http://www.oorsprong.org/websamples.countryinfo">\r
   <soapenv:Header/>\r
   <soapenv:Body>\r
      <web:ListOfLanguagesByName/>\r
   </soapenv:Body>\r
</soapenv:Envelope>]]></con:request><con:wsaConfig mustUnderstand="NONE" version="200508" action="http://www.oorsprong.org/websamples.countryinfo/CountryInfoServiceSoapType/ListOfLanguagesByNameRequest"/></con:call></con:operation></con:interface><con:testSuite id="4612b561-6f4e-4612-9288-22a6a59377c4" name="TestSuite1"><con:settings/><con:runType>SEQUENTIAL</con:runType><con:testCase id="ceb263ff-e715-48ec-a7ee-a947fc604031" failOnError="true" failTestCaseOnErrors="true" keepSession="false" maxResults="0" name="TestCase1" searchProperties="true"><con:settings/><con:testStep type="restrequest" name="getCountryByName" id="ea0fcd31-72fa-4132-94b2-8d9b15c092f2"><con:settings/><con:config service="https://restcountries.com" resourcePath="/v3.1/name/{countryName}" methodName="United 1" xsi:type="con:RestRequestStep" xmlns:xsi="http://www.w3.org/2001/XMLSchema-instance"><con:restRequest name="getCountryByName" id="bd31fe7c-cff3-418a-954f-07500b155dcf" mediaType="application/json"><con:settings><con:setting id="com.eviware.soapui.impl.wsdl.WsdlRequest@request-headers">&lt;xml-fragment/></con:setting></con:settings><con:endpoint>https://restcountries.com</con:endpoint><con:request/><con:originalUri>https://restcountries.com/v3.1/name/united</con:originalUri><con:assertion type="Simple Contains" id="903b197a-bbfc-4541-aad8-a900f1a1110c" name="Contains"><con:configuration><token>canada</token><ignoreCase>true</ignoreCase><useRegEx>false</useRegEx></con:configuration></con:assertion><con:credentials><con:authType>No Authorization</con:authType></con:credentials><con:jmsConfig JMSDeliveryMode="PERSISTENT"/><con:jmsPropertyConfig/><con:parameters><entry key="countryName" value="Canada" xmlns="http://eviware.com/soapui/config"/></con:parameters><con:parameterOrder><con:entry>countryName</con:entry></con:parameterOrder></con:restRequest></con:config></con:testStep><con:testStep type="restrequest" name="getAllCountries" id="40491bfd-09f5-4155-a6b0-271d9d40e307"><con:settings/><con:config service="https://restcountries.com" resourcePath="/v3.1/all" methodName="All 1" xsi:type="con:RestRequestStep" xmlns:xsi="http://www.w3.org/2001/XMLSchema-instance"><con:restRequest name="getAllCountries" id="9880d2f8-95d3-4672-b00a-6180a44ca53c" mediaType="application/json"><con:settings><con:setting id="com.eviware.soapui.impl.wsdl.WsdlRequest@request-headers">&lt;xml-fragment/></con:setting></con:settings><con:endpoint>https://restcountries.com</con:endpoint><con:request/><con:originalUri>https://restcountries.com/v3.1/all</con:originalUri><con:assertion type="Simple Contains" id="ebae4b96-3613-4115-bc6f-adc124a98e11" name="Contains"><con:configuration><token>africa</token><ignoreCase>true</ignoreCase><useRegEx>false</useRegEx></con:configuration></con:assertion><con:credentials><con:authType>No Authorization</con:authType></con:credentials><con:jmsConfig JMSDeliveryMode="PERSISTENT"/><con:jmsPropertyConfig/><con:parameters/></con:restRequest></con:config></con:testStep><con:properties/></con:testCase><con:testCase id="b025b652-17a0-46b1-84bf-2160c56db8c9" failOnError="true" failTestCaseOnErrors="true" keepSession="false" maxResults="0" name="ScriptedAssertions" searchProperties="true"><con:settings/><con:testStep type="restrequest" name="getCountryByName" id="86f8eebe-f1c9-42f1-9510-efaa58d673db"><con:settings/><con:config service="https://restcountries.com" resourcePath="/v3.1/name/{countryName}" methodName="United 1" xsi:type="con:RestRequestStep" xmlns:xsi="http://www.w3.org/2001/XMLSchema-instance"><con:restRequest name="getCountryByName" id="bd31fe7c-cff3-418a-954f-07500b155dcf" mediaType="application/json"><con:settings><con:setting id="com.eviware.soapui.impl.wsdl.WsdlRequest@request-headers">&lt;xml-fragment/></con:setting></con:settings><con:endpoint>https://restcountries.com</con:endpoint><con:request/><con:originalUri>https://restcountries.com/v3.1/name/united</con:originalUri><con:assertion type="Simple Contains" id="903b197a-bbfc-4541-aad8-a900f1a1110c" name="Contains"><con:configuration><token>canada</token><ignoreCase>true</ignoreCase><useRegEx>false</useRegEx></con:configuration></con:assertion><con:credentials><con:authType>No Authorization</con:authType></con:credentials><con:jmsConfig JMSDeliveryMode="PERSISTENT"/><con:jmsPropertyConfig/><con:parameters><entry key="countryName" value="canada" xmlns="http://eviware.com/soapui/config"/></con:parameters><con:parameterOrder><con:entry>countryName</con:entry></con:parameterOrder></con:restRequest></con:config></con:testStep><con:testStep type="request" id="3c1c74a8-2640-401a-a712-29c852bc3a88" name="CountryCurrency"><con:settings/><con:config xsi:type="con:RequestStep" xmlns:xsi="http://www.w3.org/2001/XMLSchema-instance"><con:interface>CountryInfoServiceSoapBinding</con:interface><con:operation>CountryCurrency</con:operation><con:request name="CountryCurrency" outgoingWss="" incomingWss="" timeout="" sslKeystore="" useWsAddressing="false" useWsReliableMessaging="false" wssPasswordType="" id="5b1f8690-e8ae-4e22-8041-35113f2ad6d2"><con:settings><con:setting id="com.eviware.soapui.impl.wsdl.WsdlRequest@request-headers">&lt;xml-fragment/></con:setting></con:settings><con:encoding>UTF-8</con:encoding><con:endpoint>http://webservices.oorsprong.org/websamples.countryinfo/CountryInfoService.wso</con:endpoint><con:request><![CDATA[<soapenv:Envelope xmlns:soapenv="http://schemas.xmlsoap.org/soap/envelope/" xmlns:web="http://www.oorsprong.org/websamples.countryinfo">\r
   <soapenv:Header/>\r
   <soapenv:Body>\r
      <web:CountryCurrency>\r
         <web:sCountryISOCode>KE</web:sCountryISOCode>\r
      </web:CountryCurrency>\r
   </soapenv:Body>\r
</soapenv:Envelope>]]></con:request><con:assertion type="SOAP Response" id="512f786c-bfe7-4d0f-85a9-ed7783d012f2" name="SOAP Response"/><con:assertion type="GroovyScriptAssertion" id="647f2f00-f1f9-42cf-9f6e-a1e3a23f8205" name="Script Assertion"><con:configuration><scriptText>//messageExchange stores details of last response

//check response time (ms)
assert messageExchange.timeTaken &lt; 400

//assert endpoint is as expected
endpoint = "http://webservices.oorsprong.org/websamples.countryinfo/CountryInfoService.wso"
assert messageExchange.getEndpoint() == endpoint

//assert header contains a certain value (might not be needed often)
assert messageExchange.responseHeaders["Content-Type"]!= null
</scriptText></con:configuration></con:assertion><con:credentials><con:authType>No Authorization</con:authType></con:credentials><con:jmsConfig JMSDeliveryMode="PERSISTENT"/><con:jmsPropertyConfig/><con:wsaConfig mustUnderstand="NONE" version="200508" action="http://www.oorsprong.org/websamples.countryinfo/CountryInfoServiceSoapType/CountryCurrencyRequest"/><con:wsrmConfig version="1.2"/></con:request></con:config></con:testStep><con:properties/></con:testCase><con:properties/></con:testSuite><con:properties/><con:wssContainer/><con:oAuth2ProfileContainer/><con:oAuth1ProfileContainer/><con:sensitiveInformation/></con:soapui-project>